{
  "meta": {
    "id": "transition-1208",
    "sourceId": 1208,
    "libraryType": "transition",
    "name": "stand up",
    "slug": "stand-up",
    "tags": [
      "stand_up",
      "top"
    ],
    "props": [
      "top"
    ],
    "frameCount": 9,
    "previewPath": "/data/library/admin/transitions/transition-1208.json"
  },
  "markers": [
    {
      "name": "stand up",
      "frame": 2,
      "type": "transition"
    }
  ],
  "frames": [
    [
      [
        [
          0.462,
          0.026,
          -0.64
        ],
        [
          0.009,
          0.027,
          -0.684
        ],
        [
          0.431,
          0.228,
          -0.532
        ],
        [
          0.084,
          0.149,
          -0.501
        ],
        [
          0.463,
          0.149,
          -0.512
        ],
        [
          0.023,
          0.088,
          -0.518
        ],
        [
          0.623,
          0.101,
          -0.116
        ],
        [
          -0.086,
          0.083,
          -0.104
        ],
        [
          0.381,
          0.336,
          -0.387
        ],
        [
          0.151,
          0.323,
          -0.374
        ],
        [
          0.422,
          0.578,
          0.14
        ],
        [
          0.081,
          0.57,
          0.119
        ],
        [
          0.46,
          0.289,
          0.138
        ],
        [
          0.033,
          0.283,
          0.11
        ],
        [
          0.39,
          0.185,
          0.369
        ],
        [
          0.158,
          0.197,
          0.335
        ],
        [
          0.373,
          0.254,
          0.411
        ],
        [
          0.165,
          0.242,
          0.404
        ],
        [
          0.314,
          0.249,
          0.467
        ],
        [
          0.232,
          0.244,
          0.447
        ],
        [
          0.273,
          0.435,
          -0.163
        ],
        [
          0.248,
          0.603,
          0.165
        ],
        [
          0.242,
          0.657,
          0.323
        ]
      ],
      [
        [
          0.241,
          0.034,
          -0.326
        ],
        [
          0.284,
          0.039,
          -0.342
        ],
        [
          0.264,
          0.03,
          -0.099
        ],
        [
          0.335,
          0.03,
          -0.117
        ],
        [
          0.204,
          0.071,
          -0.153
        ],
        [
          0.342,
          0.089,
          -0.181
        ],
        [
          -0.044,
          0.419,
          -0.109
        ],
        [
          0.575,
          0.446,
          -0.147
        ],
        [
          0.2,
          0.095,
          0.04
        ],
        [
          0.43,
          0.096,
          0.06
        ],
        [
          0.096,
          0.169,
          0.592
        ],
        [
          0.429,
          0.166,
          0.625
        ],
        [
          0.072,
          0.288,
          0.326
        ],
        [
          0.444,
          0.286,
          0.359
        ],
        [
          0.133,
          0.492,
          0.171
        ],
        [
          0.36,
          0.486,
          0.197
        ],
        [
          0.133,
          0.541,
          0.231
        ],
        [
          0.343,
          0.546,
          0.243
        ],
        [
          0.151,
          0.617,
          0.237
        ],
        [
          0.319,
          0.62,
          0.222
        ],
        [
          0.294,
          0.1,
          0.29
        ],
        [
          0.257,
          0.183,
          0.666
        ],
        [
          0.25,
          0.309,
          0.776
        ]
      ]
    ],
    [
      [
        [
          0.462,
          0.026,
          -0.64
        ],
        [
          0.009,
          0.027,
          -0.684
        ],
        [
          0.431,
          0.228,
          -0.532
        ],
        [
          0.084,
          0.149,
          -0.501
        ],
        [
          0.463,
          0.149,
          -0.512
        ],
        [
          0.023,
          0.088,
          -0.518
        ],
        [
          0.623,
          0.101,
          -0.116
        ],
        [
          -0.086,
          0.083,
          -0.104
        ],
        [
          0.381,
          0.336,
          -0.387
        ],
        [
          0.151,
          0.323,
          -0.374
        ],
        [
          0.422,
          0.578,
          0.14
        ],
        [
          0.081,
          0.57,
          0.119
        ],
        [
          0.46,
          0.289,
          0.138
        ],
        [
          0.033,
          0.283,
          0.11
        ],
        [
          0.39,
          0.185,
          0.369
        ],
        [
          0.158,
          0.197,
          0.335
        ],
        [
          0.373,
          0.254,
          0.411
        ],
        [
          0.165,
          0.242,
          0.404
        ],
        [
          0.314,
          0.249,
          0.467
        ],
        [
          0.232,
          0.244,
          0.447
        ],
        [
          0.273,
          0.435,
          -0.163
        ],
        [
          0.248,
          0.603,
          0.165
        ],
        [
          0.242,
          0.657,
          0.323
        ]
      ],
      [
        [
          0.241,
          0.034,
          -0.326
        ],
        [
          0.284,
          0.039,
          -0.342
        ],
        [
          0.264,
          0.03,
          -0.099
        ],
        [
          0.335,
          0.03,
          -0.117
        ],
        [
          0.204,
          0.071,
          -0.153
        ],
        [
          0.342,
          0.089,
          -0.181
        ],
        [
          -0.044,
          0.419,
          -0.109
        ],
        [
          0.575,
          0.446,
          -0.147
        ],
        [
          0.2,
          0.095,
          0.04
        ],
        [
          0.43,
          0.096,
          0.06
        ],
        [
          0.096,
          0.169,
          0.592
        ],
        [
          0.429,
          0.166,
          0.625
        ],
        [
          0.072,
          0.288,
          0.326
        ],
        [
          0.444,
          0.286,
          0.359
        ],
        [
          0.133,
          0.492,
          0.171
        ],
        [
          0.36,
          0.486,
          0.197
        ],
        [
          0.133,
          0.541,
          0.231
        ],
        [
          0.343,
          0.546,
          0.243
        ],
        [
          0.151,
          0.617,
          0.237
        ],
        [
          0.319,
          0.62,
          0.222
        ],
        [
          0.294,
          0.1,
          0.29
        ],
        [
          0.257,
          0.183,
          0.666
        ],
        [
          0.25,
          0.309,
          0.776
        ]
      ]
    ],
    [
      [
        [
          0.462,
          0.026,
          -0.64
        ],
        [
          0.009,
          0.027,
          -0.684
        ],
        [
          0.431,
          0.228,
          -0.532
        ],
        [
          0.084,
          0.149,
          -0.501
        ],
        [
          0.463,
          0.149,
          -0.512
        ],
        [
          0.023,
          0.088,
          -0.518
        ],
        [
          0.623,
          0.101,
          -0.116
        ],
        [
          -0.086,
          0.083,
          -0.104
        ],
        [
          0.381,
          0.336,
          -0.387
        ],
        [
          0.151,
          0.323,
          -0.374
        ],
        [
          0.422,
          0.578,
          0.14
        ],
        [
          0.081,
          0.57,
          0.119
        ],
        [
          0.46,
          0.289,
          0.138
        ],
        [
          0.033,
          0.283,
          0.11
        ],
        [
          0.39,
          0.185,
          0.369
        ],
        [
          0.158,
          0.197,
          0.335
        ],
        [
          0.373,
          0.254,
          0.411
        ],
        [
          0.165,
          0.242,
          0.404
        ],
        [
          0.314,
          0.249,
          0.467
        ],
        [
          0.232,
          0.244,
          0.447
        ],
        [
          0.273,
          0.435,
          -0.163
        ],
        [
          0.248,
          0.603,
          0.165
        ],
        [
          0.242,
          0.657,
          0.323
        ]
      ],
      [
        [
          0.241,
          0.034,
          -0.326
        ],
        [
          0.284,
          0.039,
          -0.342
        ],
        [
          0.264,
          0.03,
          -0.099
        ],
        [
          0.335,
          0.03,
          -0.117
        ],
        [
          0.204,
          0.071,
          -0.153
        ],
        [
          0.342,
          0.089,
          -0.181
        ],
        [
          -0.044,
          0.419,
          -0.109
        ],
        [
          0.575,
          0.446,
          -0.147
        ],
        [
          0.2,
          0.095,
          0.04
        ],
        [
          0.43,
          0.096,
          0.06
        ],
        [
          0.096,
          0.169,
          0.592
        ],
        [
          0.429,
          0.166,
          0.625
        ],
        [
          0.072,
          0.288,
          0.326
        ],
        [
          0.444,
          0.286,
          0.359
        ],
        [
          0.133,
          0.492,
          0.171
        ],
        [
          0.36,
          0.486,
          0.197
        ],
        [
          0.133,
          0.541,
          0.231
        ],
        [
          0.343,
          0.546,
          0.243
        ],
        [
          0.151,
          0.617,
          0.237
        ],
        [
          0.319,
          0.62,
          0.222
        ],
        [
          0.294,
          0.1,
          0.29
        ],
        [
          0.257,
          0.183,
          0.666
        ],
        [
          0.25,
          0.309,
          0.776
        ]
      ]
    ],
    [
      [
        [
          0.5,
          0.026,
          -0.6385
        ],
        [
          0.027,
          0.0275,
          -0.3415
        ],
        [
          0.4545,
          0.2285,
          -0.541
        ],
        [
          0.0755,
          0.113,
          -0.362
        ],
        [
          0.4905,
          0.1525,
          -0.511
        ],
        [
          0.0375,
          0.107,
          -0.3335
        ],
        [
          0.6365,
          0.0855,
          -0.112
        ],
        [
          -0.0645,
          0.2825,
          -0.017
        ],
        [
          0.401,
          0.377,
          -0.3015
        ],
        [
          0.178,
          0.3965,
          -0.329
        ],
        [
          0.4365,
          0.6435,
          0.1805
        ],
        [
          0.0995,
          0.623,
          0.159
        ],
        [
          0.464,
          0.355,
          0.158
        ],
        [
          0.095,
          0.342,
          0.119
        ],
        [
          0.396,
          0.1935,
          0.3385
        ],
        [
          0.1825,
          0.1975,
          0.319
        ],
        [
          0.3885,
          0.2565,
          0.388
        ],
        [
          0.1725,
          0.2345,
          0.3895
        ],
        [
          0.3455,
          0.245,
          0.4535
        ],
        [
          0.22,
          0.2175,
          0.4455
        ],
        [
          0.293,
          0.541,
          -0.1385
        ],
        [
          0.2635,
          0.66,
          0.2095
        ],
        [
          0.2605,
          0.6925,
          0.3705
        ]
      ],
      [
        [
          0.199,
          0.1675,
          -0.3305
        ],
        [
          0.2865,
          0.143,
          -0.301
        ],
        [
          0.2685,
          0.118,
          -0.131
        ],
        [
          0.267,
          0.1095,
          -0.086
        ],
        [
          0.195,
          0.1535,
          -0.1605
        ],
        [
          0.3125,
          0.1495,
          -0.134
        ],
        [
          -0.0095,
          0.464,
          0.009
        ],
        [
          0.6,
          0.454,
          -0.0775
        ],
        [
          0.1915,
          0.106,
          0.041
        ],
        [
          0.42,
          0.0955,
          0.0515
        ],
        [
          0.103,
          0.144,
          0.601
        ],
        [
          0.4285,
          0.149,
          0.6275
        ],
        [
          0.0405,
          0.2355,
          0.336
        ],
        [
          0.4835,
          0.244,
          0.362
        ],
        [
          0.1045,
          0.461,
          0.2295
        ],
        [
          0.4175,
          0.4725,
          0.2445
        ],
        [
          0.1195,
          0.5195,
          0.273
        ],
        [
          0.3975,
          0.54,
          0.2735
        ],
        [
          0.1355,
          0.5905,
          0.257
        ],
        [
          0.3805,
          0.6055,
          0.2375
        ],
        [
          0.2945,
          0.1,
          0.2885
        ],
        [
          0.2605,
          0.172,
          0.6715
        ],
        [
          0.2575,
          0.2835,
          0.7925
        ]
      ]
    ],
    [
      [
        [
          0.538,
          0.026,
          -0.637
        ],
        [
          0.045,
          0.028,
          0.001
        ],
        [
          0.478,
          0.229,
          -0.55
        ],
        [
          0.067,
          0.077,
          -0.223
        ],
        [
          0.518,
          0.156,
          -0.51
        ],
        [
          0.052,
          0.126,
          -0.149
        ],
        [
          0.65,
          0.07,
          -0.108
        ],
        [
          -0.043,
          0.482,
          0.07
        ],
        [
          0.421,
          0.418,
          -0.216
        ],
        [
          0.205,
          0.47,
          -0.284
        ],
        [
          0.451,
          0.709,
          0.221
        ],
        [
          0.118,
          0.676,
          0.199
        ],
        [
          0.468,
          0.421,
          0.178
        ],
        [
          0.157,
          0.401,
          0.128
        ],
        [
          0.402,
          0.202,
          0.308
        ],
        [
          0.207,
          0.198,
          0.303
        ],
        [
          0.404,
          0.259,
          0.365
        ],
        [
          0.18,
          0.227,
          0.375
        ],
        [
          0.377,
          0.241,
          0.44
        ],
        [
          0.208,
          0.191,
          0.444
        ],
        [
          0.313,
          0.647,
          -0.114
        ],
        [
          0.279,
          0.717,
          0.254
        ],
        [
          0.279,
          0.728,
          0.418
        ]
      ],
      [
        [
          0.157,
          0.301,
          -0.335
        ],
        [
          0.289,
          0.247,
          -0.26
        ],
        [
          0.273,
          0.206,
          -0.163
        ],
        [
          0.199,
          0.189,
          -0.055
        ],
        [
          0.186,
          0.236,
          -0.168
        ],
        [
          0.283,
          0.21,
          -0.087
        ],
        [
          0.025,
          0.509,
          0.127
        ],
        [
          0.625,
          0.462,
          -0.008
        ],
        [
          0.183,
          0.117,
          0.042
        ],
        [
          0.41,
          0.095,
          0.043
        ],
        [
          0.11,
          0.119,
          0.61
        ],
        [
          0.428,
          0.132,
          0.63
        ],
        [
          0.009,
          0.183,
          0.346
        ],
        [
          0.523,
          0.202,
          0.365
        ],
        [
          0.076,
          0.43,
          0.288
        ],
        [
          0.475,
          0.459,
          0.292
        ],
        [
          0.106,
          0.498,
          0.315
        ],
        [
          0.452,
          0.534,
          0.304
        ],
        [
          0.12,
          0.564,
          0.277
        ],
        [
          0.442,
          0.591,
          0.253
        ],
        [
          0.295,
          0.1,
          0.287
        ],
        [
          0.264,
          0.161,
          0.677
        ],
        [
          0.265,
          0.258,
          0.809
        ]
      ]
    ],
    [
      [
        [
          0.538,
          0.026,
          -0.637
        ],
        [
          0.045,
          0.028,
          0.001
        ],
        [
          0.478,
          0.229,
          -0.55
        ],
        [
          0.067,
          0.077,
          -0.223
        ],
        [
          0.518,
          0.156,
          -0.51
        ],
        [
          0.052,
          0.126,
          -0.149
        ],
        [
          0.65,
          0.07,
          -0.108
        ],
        [
          -0.043,
          0.482,
          0.07
        ],
        [
          0.421,
          0.418,
          -0.216
        ],
        [
          0.205,
          0.47,
          -0.284
        ],
        [
          0.451,
          0.709,
          0.221
        ],
        [
          0.118,
          0.676,
          0.199
        ],
        [
          0.468,
          0.421,
          0.178
        ],
        [
          0.157,
          0.401,
          0.128
        ],
        [
          0.402,
          0.202,
          0.308
        ],
        [
          0.207,
          0.198,
          0.303
        ],
        [
          0.404,
          0.259,
          0.365
        ],
        [
          0.18,
          0.227,
          0.375
        ],
        [
          0.377,
          0.241,
          0.44
        ],
        [
          0.208,
          0.191,
          0.444
        ],
        [
          0.313,
          0.647,
          -0.114
        ],
        [
          0.279,
          0.717,
          0.254
        ],
        [
          0.279,
          0.728,
          0.418
        ]
      ],
      [
        [
          0.157,
          0.301,
          -0.335
        ],
        [
          0.289,
          0.247,
          -0.26
        ],
        [
          0.273,
          0.206,
          -0.163
        ],
        [
          0.199,
          0.189,
          -0.055
        ],
        [
          0.186,
          0.236,
          -0.168
        ],
        [
          0.283,
          0.21,
          -0.087
        ],
        [
          0.025,
          0.509,
          0.127
        ],
        [
          0.625,
          0.462,
          -0.008
        ],
        [
          0.183,
          0.117,
          0.042
        ],
        [
          0.41,
          0.095,
          0.043
        ],
        [
          0.11,
          0.119,
          0.61
        ],
        [
          0.428,
          0.132,
          0.63
        ],
        [
          0.009,
          0.183,
          0.346
        ],
        [
          0.523,
          0.202,
          0.365
        ],
        [
          0.076,
          0.43,
          0.288
        ],
        [
          0.475,
          0.459,
          0.292
        ],
        [
          0.106,
          0.498,
          0.315
        ],
        [
          0.452,
          0.534,
          0.304
        ],
        [
          0.12,
          0.564,
          0.277
        ],
        [
          0.442,
          0.591,
          0.253
        ],
        [
          0.295,
          0.1,
          0.287
        ],
        [
          0.264,
          0.161,
          0.677
        ],
        [
          0.265,
          0.258,
          0.809
        ]
      ]
    ],
    [
      [
        [
          0.538,
          0.026,
          -0.637
        ],
        [
          0.045,
          0.028,
          0.001
        ],
        [
          0.478,
          0.229,
          -0.55
        ],
        [
          0.067,
          0.077,
          -0.223
        ],
        [
          0.518,
          0.156,
          -0.51
        ],
        [
          0.052,
          0.126,
          -0.149
        ],
        [
          0.65,
          0.07,
          -0.108
        ],
        [
          -0.043,
          0.482,
          0.07
        ],
        [
          0.421,
          0.418,
          -0.216
        ],
        [
          0.205,
          0.47,
          -0.284
        ],
        [
          0.451,
          0.709,
          0.221
        ],
        [
          0.118,
          0.676,
          0.199
        ],
        [
          0.468,
          0.421,
          0.178
        ],
        [
          0.157,
          0.401,
          0.128
        ],
        [
          0.402,
          0.202,
          0.308
        ],
        [
          0.207,
          0.198,
          0.303
        ],
        [
          0.404,
          0.259,
          0.365
        ],
        [
          0.18,
          0.227,
          0.375
        ],
        [
          0.377,
          0.241,
          0.44
        ],
        [
          0.208,
          0.191,
          0.444
        ],
        [
          0.313,
          0.647,
          -0.114
        ],
        [
          0.279,
          0.717,
          0.254
        ],
        [
          0.279,
          0.728,
          0.418
        ]
      ],
      [
        [
          0.157,
          0.301,
          -0.335
        ],
        [
          0.289,
          0.247,
          -0.26
        ],
        [
          0.273,
          0.206,
          -0.163
        ],
        [
          0.199,
          0.189,
          -0.055
        ],
        [
          0.186,
          0.236,
          -0.168
        ],
        [
          0.283,
          0.21,
          -0.087
        ],
        [
          0.025,
          0.509,
          0.127
        ],
        [
          0.625,
          0.462,
          -0.008
        ],
        [
          0.183,
          0.117,
          0.042
        ],
        [
          0.41,
          0.095,
          0.043
        ],
        [
          0.11,
          0.119,
          0.61
        ],
        [
          0.428,
          0.132,
          0.63
        ],
        [
          0.009,
          0.183,
          0.346
        ],
        [
          0.523,
          0.202,
          0.365
        ],
        [
          0.076,
          0.43,
          0.288
        ],
        [
          0.475,
          0.459,
          0.292
        ],
        [
          0.106,
          0.498,
          0.315
        ],
        [
          0.452,
          0.534,
          0.304
        ],
        [
          0.12,
          0.564,
          0.277
        ],
        [
          0.442,
          0.591,
          0.253
        ],
        [
          0.295,
          0.1,
          0.287
        ],
        [
          0.264,
          0.161,
          0.677
        ],
        [
          0.265,
          0.258,
          0.809
        ]
      ]
    ],
    [
      [
        [
          0.538,
          0.026,
          -0.637
        ],
        [
          0.045,
          0.028,
          0.001
        ],
        [
          0.478,
          0.229,
          -0.55
        ],
        [
          0.067,
          0.077,
          -0.223
        ],
        [
          0.518,
          0.156,
          -0.51
        ],
        [
          0.052,
          0.126,
          -0.149
        ],
        [
          0.65,
          0.07,
          -0.108
        ],
        [
          -0.043,
          0.482,
          0.07
        ],
        [
          0.421,
          0.418,
          -0.216
        ],
        [
          0.205,
          0.47,
          -0.284
        ],
        [
          0.451,
          0.709,
          0.221
        ],
        [
          0.118,
          0.676,
          0.199
        ],
        [
          0.468,
          0.421,
          0.178
        ],
        [
          0.157,
          0.401,
          0.128
        ],
        [
          0.402,
          0.202,
          0.308
        ],
        [
          0.207,
          0.198,
          0.303
        ],
        [
          0.404,
          0.259,
          0.365
        ],
        [
          0.18,
          0.227,
          0.375
        ],
        [
          0.377,
          0.241,
          0.44
        ],
        [
          0.208,
          0.191,
          0.444
        ],
        [
          0.313,
          0.647,
          -0.114
        ],
        [
          0.279,
          0.717,
          0.254
        ],
        [
          0.279,
          0.728,
          0.418
        ]
      ],
      [
        [
          0.157,
          0.301,
          -0.335
        ],
        [
          0.289,
          0.247,
          -0.26
        ],
        [
          0.273,
          0.206,
          -0.163
        ],
        [
          0.199,
          0.189,
          -0.055
        ],
        [
          0.186,
          0.236,
          -0.168
        ],
        [
          0.283,
          0.21,
          -0.087
        ],
        [
          0.025,
          0.509,
          0.127
        ],
        [
          0.625,
          0.462,
          -0.008
        ],
        [
          0.183,
          0.117,
          0.042
        ],
        [
          0.41,
          0.095,
          0.043
        ],
        [
          0.11,
          0.119,
          0.61
        ],
        [
          0.428,
          0.132,
          0.63
        ],
        [
          0.009,
          0.183,
          0.346
        ],
        [
          0.523,
          0.202,
          0.365
        ],
        [
          0.076,
          0.43,
          0.288
        ],
        [
          0.475,
          0.459,
          0.292
        ],
        [
          0.106,
          0.498,
          0.315
        ],
        [
          0.452,
          0.534,
          0.304
        ],
        [
          0.12,
          0.564,
          0.277
        ],
        [
          0.442,
          0.591,
          0.253
        ],
        [
          0.295,
          0.1,
          0.287
        ],
        [
          0.264,
          0.161,
          0.677
        ],
        [
          0.265,
          0.258,
          0.809
        ]
      ]
    ],
    [
      [
        [
          0.538,
          0.026,
          -0.637
        ],
        [
          0.045,
          0.028,
          0.001
        ],
        [
          0.478,
          0.229,
          -0.55
        ],
        [
          0.067,
          0.077,
          -0.223
        ],
        [
          0.518,
          0.156,
          -0.51
        ],
        [
          0.052,
          0.126,
          -0.149
        ],
        [
          0.65,
          0.07,
          -0.108
        ],
        [
          -0.043,
          0.482,
          0.07
        ],
        [
          0.421,
          0.418,
          -0.216
        ],
        [
          0.205,
          0.47,
          -0.284
        ],
        [
          0.451,
          0.709,
          0.221
        ],
        [
          0.118,
          0.676,
          0.199
        ],
        [
          0.468,
          0.421,
          0.178
        ],
        [
          0.157,
          0.401,
          0.128
        ],
        [
          0.402,
          0.202,
          0.308
        ],
        [
          0.207,
          0.198,
          0.303
        ],
        [
          0.404,
          0.259,
          0.365
        ],
        [
          0.18,
          0.227,
          0.375
        ],
        [
          0.377,
          0.241,
          0.44
        ],
        [
          0.208,
          0.191,
          0.444
        ],
        [
          0.313,
          0.647,
          -0.114
        ],
        [
          0.279,
          0.717,
          0.254
        ],
        [
          0.279,
          0.728,
          0.418
        ]
      ],
      [
        [
          0.157,
          0.301,
          -0.335
        ],
        [
          0.289,
          0.247,
          -0.26
        ],
        [
          0.273,
          0.206,
          -0.163
        ],
        [
          0.199,
          0.189,
          -0.055
        ],
        [
          0.186,
          0.236,
          -0.168
        ],
        [
          0.283,
          0.21,
          -0.087
        ],
        [
          0.025,
          0.509,
          0.127
        ],
        [
          0.625,
          0.462,
          -0.008
        ],
        [
          0.183,
          0.117,
          0.042
        ],
        [
          0.41,
          0.095,
          0.043
        ],
        [
          0.11,
          0.119,
          0.61
        ],
        [
          0.428,
          0.132,
          0.63
        ],
        [
          0.009,
          0.183,
          0.346
        ],
        [
          0.523,
          0.202,
          0.365
        ],
        [
          0.076,
          0.43,
          0.288
        ],
        [
          0.475,
          0.459,
          0.292
        ],
        [
          0.106,
          0.498,
          0.315
        ],
        [
          0.452,
          0.534,
          0.304
        ],
        [
          0.12,
          0.564,
          0.277
        ],
        [
          0.442,
          0.591,
          0.253
        ],
        [
          0.295,
          0.1,
          0.287
        ],
        [
          0.264,
          0.161,
          0.677
        ],
        [
          0.265,
          0.258,
          0.809
        ]
      ]
    ]
  ]
}